CrowdStrike/__init__.py
CrowdStrike/api.py
CrowdStrike/detection_parser.py
config/__init__.py
config/config.py
CrowdStrike2TH-0.0.9.dist-info/LICENSE
CrowdStrike2TH-0.0.9.dist-info/METADATA
CrowdStrike2TH-0.0.9.dist-info/WHEEL
CrowdStrike2TH-0.0.9.dist-info/top_level.txt
CrowdStrike2TH-0.0.9.dist-info/RECORD
