Metadata-Version: 2.1
Name: CrowdStrike2TH
Version: 0.0.9
Summary: Falcon CrowdStrike Alert Feeder for TheHive
Home-page: https://github.com/Sshahar/CrowdStrike2TH/
Author: Shahar Margalit
Author-email: shaharma@gmail.com
License: UNKNOWN
Project-URL: Bug Tracker, https://github.com/Sshahar/CrowdStrike2TH//issues
Platform: UNKNOWN
Classifier: Programming Language :: Python :: 3
Classifier: License :: OSI Approved :: GNU General Public License v3 (GPLv3)
Classifier: Operating System :: OS Independent
Requires-Python: >=3.6
License-File: LICENSE
